AUTHORS
CHANGES
LICENSE
MANIFEST.in
README
setup.py
pygrowup/__init__.py
pygrowup/__init__.pyc
pygrowup/exceptions.py
pygrowup/exceptions.pyc
pygrowup/helpers.py
pygrowup/pygrowup.py
pygrowup/pygrowup.pyc
pygrowup/tests.py
pygrowup.egg-info/PKG-INFO
pygrowup.egg-info/SOURCES.txt
pygrowup.egg-info/dependency_links.txt
pygrowup.egg-info/pbr.json
pygrowup.egg-info/requires.txt
pygrowup.egg-info/top_level.txt
pygrowup/__pycache__/__init__.cpython-34.pyc
pygrowup/__pycache__/exceptions.cpython-34.pyc
pygrowup/__pycache__/pygrowup.cpython-34.pyc
pygrowup/__pycache__/tests.cpython-34.pyc
pygrowup/tables/bmifa_boys_0_13_zscores.json
pygrowup/tables/bmifa_boys_0_2_zscores.json
pygrowup/tables/bmifa_boys_2_20_zscores.cdc.json
pygrowup/tables/bmifa_boys_2_5_zscores.json
pygrowup/tables/bmifa_girls_0_13_zscores.json
pygrowup/tables/bmifa_girls_0_2_zscores.json
pygrowup/tables/bmifa_girls_2_20_zscores.cdc.json
pygrowup/tables/bmifa_girls_2_5_zscores.json
pygrowup/tables/hcfa_boys_0_13_zscores.json
pygrowup/tables/hcfa_boys_0_5_zscores.json
pygrowup/tables/hcfa_girls_0_13_zscores.json
pygrowup/tables/hcfa_girls_0_5_zscores.json
pygrowup/tables/lhfa_boys_0_13_zscores.json
pygrowup/tables/lhfa_boys_0_2_zscores.json
pygrowup/tables/lhfa_boys_0_5_zscores.json
pygrowup/tables/lhfa_boys_2_20_zscores.cdc.json
pygrowup/tables/lhfa_boys_2_5_zscores.json
pygrowup/tables/lhfa_girls_0_13_zscores.json
pygrowup/tables/lhfa_girls_0_2_zscores.json
pygrowup/tables/lhfa_girls_0_5_zscores.json
pygrowup/tables/lhfa_girls_2_20_zscores.cdc.json
pygrowup/tables/lhfa_girls_2_5_zscores.json
pygrowup/tables/wfa_boys_0_13_zscores.json
pygrowup/tables/wfa_boys_0_5_zscores.json
pygrowup/tables/wfa_boys_2_20_zscores.cdc.json
pygrowup/tables/wfa_girls_0_13_zscores.json
pygrowup/tables/wfa_girls_0_5_zscores.json
pygrowup/tables/wfa_girls_2_20_zscores.cdc.json
pygrowup/tables/wfh_boys_2_5_zscores.json
pygrowup/tables/wfh_girls_2_5_zscores.json
pygrowup/tables/wfl_boys_0_2_zscores.json
pygrowup/tables/wfl_girls_0_2_zscores.json
pygrowup/tables/source/cdc/bmiage.csv
pygrowup/tables/source/cdc/statage.csv
pygrowup/tables/source/cdc/wtage.csv
pygrowup/tables/source/cdc/zbmiage.csv
