Metadata-Version: 1.1
Name: pygrowup
Version: 0.8.2
Summary: Calculate z-scores of anthropometric measurements based on WHO and CDC child growth standards
Home-page: http://github.com/ewheeler/pygrowup
Author: Evan Wheeler
Author-email: evanmwheeler@gmail.com
License: BSD
Download-URL: https://github.com/ewheeler/pygrowup/archive/0.8.2.tar.gz
Platform: UNKNOWN
Classifier: Intended Audience :: Healthcare Industry
Classifier: Programming Language :: Python
Classifier: Programming Language :: Python :: 2.7
Classifier: Programming Language :: Python :: 3
Classifier: License :: OSI Approved :: BSD License
Classifier: Topic :: Scientific/Engineering :: Bio-Informatics
Classifier: Operating System :: MacOS :: MacOS X
Classifier: Operating System :: Microsoft :: Windows
Classifier: Operating System :: POSIX
